django_html_sanitizer-0.1.5.dist-info/METADATA
django_html_sanitizer-0.1.5.dist-info/WHEEL
django_html_sanitizer-0.1.5.dist-info/top_level.txt
django_html_sanitizer-0.1.5.dist-info/RECORD
django_html_sanitizer-0.1.5.dist-info/pbr.json
django_html_sanitizer-0.1.5.dist-info/DESCRIPTION.rst
django_html_sanitizer-0.1.5.dist-info/metadata.json
sanitizer/tests.py
sanitizer/models.py
sanitizer/__init__.py
sanitizer/decorators.py
sanitizer/forms.py
sanitizer/templatetags/sanitizer.py
sanitizer/templatetags/__init__.py
