Metadata-Version: 1.1
Name: django-html_sanitizer
Version: 0.1.5
Summary: Provides a set of HTML cleaning utilities for django models, forms and templates.
Home-page: https://github.com/ui/django-html_sanitizer
Author: Selwin Ong
Author-email: selwin.ong@gmail.com
License: MIT
Platform: UNKNOWN
Classifier: Development Status :: 4 - Beta
Classifier: Environment :: Web Environment
Classifier: Framework :: Django
Classifier: Intended Audience :: Developers
Classifier: License :: OSI Approved :: MIT License
Classifier: Operating System :: OS Independent
Classifier: Programming Language :: Python
Classifier: Topic :: Internet :: WWW/HTTP
Classifier: Topic :: Software Development :: Libraries :: Python Modules
Classifier: Topic :: Text Processing :: Markup :: HTML
